define.py
python_define-3.0.0.dist-info/LICENSE
python_define-3.0.0.dist-info/METADATA
python_define-3.0.0.dist-info/WHEEL
python_define-3.0.0.dist-info/entry_points.txt
python_define-3.0.0.dist-info/top_level.txt
python_define-3.0.0.dist-info/RECORD
