Metadata-Version: 2.1
Name: python-define
Version: 3.0.0
Summary: An AI-powered command-line linguistics assistant
Author-email: Grant Carthew <grant@carthew.net>
Maintainer-email: Grant Carthew <grant@carthew.net>
License: Mozilla Public License Version 2.0
Project-URL: Homepage, https://github.com/grantcarthew/python-define
Project-URL: Documentation, https://github.com/grantcarthew/python-define
Project-URL: Repository, https://github.com/grantcarthew/python-define.git
Project-URL: Changelog, https://github.com/grantcarthew/python-define/commits/main
Keywords: define,ai,llm,x.ai,xai,anthropic,openai,chatgpt,gpt,english,linguistics,cli
Requires-Python: >=3.8
License-File: LICENSE
Requires-Dist: Click ~=8.1.7
Requires-Dist: openai ~=1.25.0
